[{
  "_id": {
    "$oid": "5e319ca80f840854bf7e0f96"
  },
  "notificationID": "shaileshgupta59629489",
  "email_id": "shaileshgupta596@gmail.com",
  "message": "File PAN06966 at your desk is delayed by 20 days!",
  "timeCreated": {
    "$date": "2020-01-29T20:24:32.294Z"
  },
  "read": true
},{
  "_id": {
    "$oid": "5e31a21c54caf19c9c3083c8"
  },
  "notificationID": "shaileshgupta59690264",
  "email_id": "shaileshgupta596@gmail.com",
  "message": "File PAN06966 at your desk is delayed by 1 days!",
  "timeCreated": {
    "$date": "2020-01-29T20:47:48.902Z"
  },
  "read": true
},{
  "_id": {
    "$oid": "5e31a226e2cc7e21acc339cf"
  },
  "notificationID": "shaileshgupta59616821",
  "email_id": "shaileshgupta596@gmail.com",
  "message": "File PAN06966 at your desk is delayed by 10days!",
  "timeCreated": {
    "$date": "2020-01-29T20:47:58.168Z"
  },
  "read": true
},{
  "_id": {
    "$oid": "5e31a232df393574310bc0a2"
  },
  "notificationID": "shaileshgupta59633093",
  "email_id": "shaileshgupta596@gmail.com",
  "message": "File PAN06966 at your desk is delayed by 1 days!",
  "timeCreated": {
    "$date": "2020-01-29T20:48:10.330Z"
  },
  "read": true
},{
  "_id": {
    "$oid": "5e3651fb96a81a2682b71210"
  },
  "notificationID": "abygpta1580618235.48016",
  "email_id": "abygpta@gmail.com",
  "message": "File PAN94870 at your desk is delayed by 3 days!",
  "timeCreated": {
    "$date": "2020-02-02T10:07:15.480Z"
  },
  "read": false
},{
  "_id": {
    "$oid": "5e37cf017f7f10c881886427"
  },
  "notificationID": "abygpta1580715777.567272",
  "email_id": "abygpta@gmail.com",
  "message": "File PAN94870 at your desk is delayed by 4 days!",
  "timeCreated": {
    "$date": "2020-02-03T13:12:57.567Z"
  },
  "read": false
},{
  "_id": {
    "$oid": "5e37d97d8607d66045b69e81"
  },
  "notificationID": "abygpta1580718461",
  "email_id": "abygpta@gmail.com",
  "message": "File PAN94870 at your desk is delayed by 4 days!",
  "timeCreated": {
    "$date": "2020-02-03T13:57:41.476Z"
  },
  "read": false
},{
  "_id": {
    "$oid": "5e37dfd734b8cb466d21f84c"
  },
  "notificationID": "chavanrachit16e1580720087",
  "email_id": "chavanrachit16e@student.mes.ac.in",
  "message": "File PAN99384 at your desk is delayed by 2 days!",
  "timeCreated": {
    "$date": "2020-02-03T14:24:47.880Z"
  },
  "read": true
},{
  "_id": {
    "$oid": "5e37dfdd34b8cb466d21f84d"
  },
  "notificationID": "abygpta1580720093",
  "email_id": "abygpta@gmail.com",
  "message": "File PAN94870 at your desk is delayed by 4 days!",
  "timeCreated": {
    "$date": "2020-02-03T14:24:53.986Z"
  },
  "read": false
}]